{"_id":{"$oid":"633bf15e5337fd7e72331768"},"username":"TheHound","email":"hound@gmai.com","password":"$2a$12$fokRqSnXfOs8fDMmJnFJC.IGfzEAwUqOlMNJKS2TUmCqwMq0s/Ybq","image":"/uploads/images/96347167.jpeg","createdAt":{"$date":"2022-10-04T08:21:54.768Z"},"__v":0}
{"_id":{"$oid":"633bf4f85337fd7e72331774"},"username":"Ragnar Lothbrok","email":"ragnar@gmail.com","password":"$2a$12$KRWd1r1KeLaamchg3fwoAuLqpV29/4qIdiBupMS477X9QtRjqSCcm","image":"/uploads/images/68089459.jpeg","createdAt":{"$date":"2022-10-04T08:21:54.768Z"},"__v":0}
{"_id":{"$oid":"633bf92f6d9db40d51543b98"},"username":"harry potter","email":"harry@gmail.com","password":"$2a$12$8j97S5Aw4ZcmIeC7LBx1Auo12n5C9SiwCb4VLZBgQ.Lf2/mXwKx8e","image":"/uploads/images/80407641.jpeg","createdAt":{"$date":"2022-10-04T09:12:26.079Z"},"__v":0}
{"_id":{"$oid":"633bef835337fd7e72331756"},"username":"jackthecoder","email":"jack@gmail.com","password":"$2a$12$fokRqSnXfOs8fDMmJnFJC.IGfzEAwUqOlMNJKS2TUmCqwMq0s/Ybq","image":"/uploads/images/29563265.jpeg","createdAt":{"$date":"2022-10-04T08:21:54.768Z"},"__v":0}
{"_id":{"$oid":"633beddc5337fd7e72331748"},"username":"thomasthecat","email":"thomas@gmail.com","password":"$2a$12$KeO4zS2OEsuWwMJgvBYfz.2kE3cK4cG6K6YStLzQ1Tvt.y1Ba09NC","image":"/uploads/images/68283306.png","createdAt":{"$date":"2022-10-04T08:21:54.768Z"},"__v":0}
{"_id":{"$oid":"633bf5b85337fd7e7233177f"},"username":"Charles Blessing","email":"charles@gmail.com","password":"$2a$12$cCTtRJiq/CLl4bbk7uSNIu.w8lo94Yu3Hrs55Ier9iis/eRorr8wC","image":"/uploads/images/31987691.jpeg","createdAt":{"$date":"2022-10-04T08:21:54.768Z"},"__v":0}
